shape/_gem.py
shape/point.py
gemplib-0.0.1.dist-info/LICENSE
gemplib-0.0.1.dist-info/METADATA
gemplib-0.0.1.dist-info/WHEEL
gemplib-0.0.1.dist-info/top_level.txt
gemplib-0.0.1.dist-info/RECORD
